ascend_sdk/__init__.py
ascend_sdk/_hooks/__init__.py
ascend_sdk/_hooks/apex_access_token_hook.py
ascend_sdk/_hooks/registration.py
ascend_sdk/_hooks/sdkhooks.py
ascend_sdk/_hooks/types.py
ascend_sdk/_version.py
ascend_sdk/account_creation.py
ascend_sdk/account_management.py
ascend_sdk/account_transfers.py
ascend_sdk/ach_transfers.py
ascend_sdk/asset_trading_config.py
ascend_sdk/assets.py
ascend_sdk/authentication.py
ascend_sdk/bank_relationships.py
ascend_sdk/basesdk.py
ascend_sdk/basket_orders.py
ascend_sdk/cash_balances.py
ascend_sdk/checks.py
ascend_sdk/data_retrieval.py
ascend_sdk/enrollments_and_agreements.py
ascend_sdk/fees_and_credits.py
ascend_sdk/fixed_income_pricing.py
ascend_sdk/httpclient.py
ascend_sdk/instant_cash_transfer_ict_.py
ascend_sdk/investigations.py
ascend_sdk/investor_docs.py
ascend_sdk/journals.py
ascend_sdk/ledger.py
ascend_sdk/margins.py
ascend_sdk/models/__init__.py
ascend_sdk/models/components/__init__.py
ascend_sdk/models/components/acatsasset.py
ascend_sdk/models/components/acatstransfer.py
ascend_sdk/models/components/accepttransferrequestcreate.py
ascend_sdk/models/components/accepttransferresponse.py
ascend_sdk/models/components/account.py
ascend_sdk/models/components/accountdocumentuploadrequestcreate.py
ascend_sdk/models/components/accountgoalscreate.py
ascend_sdk/models/components/accountgoalsupdate.py
ascend_sdk/models/components/accountrequestcreate.py
ascend_sdk/models/components/accountrequestupdate.py
ascend_sdk/models/components/accounttaxprofilecreate.py
ascend_sdk/models/components/accounttaxprofileupdate.py
ascend_sdk/models/components/accruedinterest.py
ascend_sdk/models/components/achdeposit.py
ascend_sdk/models/components/achdepositcreate.py
ascend_sdk/models/components/achdepositschedule.py
ascend_sdk/models/components/achdepositschedulecreate.py
ascend_sdk/models/components/achdepositscheduleupdate.py
ascend_sdk/models/components/achwithdrawal.py
ascend_sdk/models/components/achwithdrawalcreate.py
ascend_sdk-1.8.2.dist-info/METADATA
ascend_sdk-1.8.2.dist-info/WHEEL
ascend_sdk-1.8.2.dist-info/RECORD
