Metadata-Version: 2.4
Name: ascend-sdk
Version: 1.8.2
Summary: Python Client SDK for Apex Ascend Platform
License: MIT
Author: Apex Fintech Solutions
Requires-Python: >=3.9.2
Classifier: License :: OSI Approved :: MIT License
Classifier: Programming Language :: Python :: 3
Classifier: Programming Language :: Python :: 3.10
Classifier: Programming Language :: Python :: 3.11
Classifier: Programming Language :: Python :: 3.12
Classifier: Programming Language :: Python :: 3.13
Classifier: Programming Language :: Python :: 3.14
Requires-Dist: PyJWT (>=2.4.0,<3.0.0)
Requires-Dist: cryptography (>=43.0.0)
Requires-Dist: httpcore (>=1.0.9)
Requires-Dist: httpx (>=0.28.1)
Requires-Dist: jsonpath-python (>=1.0.6)
Requires-Dist: pydantic (>=2.11.2)
Requires-Dist: requests (>=2.32.3,<3.0.0)
